{"province":"辽宁","bestTime":"最佳时间：5月-10月","foods":[{"name":"海鲜焖子","rating":5,"tags":["大连风味","咸鲜香滑"],"intro":"地瓜淀粉制成的焖子煎至两面金黄焦脆，淋上芝麻酱、蒜泥，配以鲜大虾、八爪鱼，极鲜美。","image":"assets/images/foods/liaoning_haixianmenzi.jpg","city":"其他"},{"name":"锦州烧烤","rating":4.6,"tags":["深夜食堂","香辣过瘾"],"intro":"手法独特，调料丰富。肉串、排骨、海鲜在炭火上猛烈翻烤，撒上孜然辣椒，外焦里嫩。","image":"assets/images/foods/liaoning_j7ixcl.jpg","city":"其他"},{"name":"沟帮子熏鸡","rating":4.4,"tags":["关东名产","烂烂脱骨"],"intro":"色泽红亮，鸡肉烟熏味浓郁，肉质细嫩，酥烂脱骨，咸香可口。","image":"assets/images/foods/liaoning_asb5rn.jpg","city":"其他"},{"name":"老边饺子","rating":4.7,"tags":["百年传承","煸馅独特"],"intro":"沈阳传统名小吃，饺子馅先煸后拌，皮薄馅饱，多汁鲜美，口感极佳。","image":"assets/images/foods/liaoning_laobianjiaozi.jpg","city":"其他"},{"name":"沈阳鸡架","rating":4.9,"tags":["夜宵灵魂","啃骨嘬味"],"intro":"全国消耗鸡架最多的城市，可烤、可炸、可煮、可熏，虽然肉不多，但骨边的肉极其入味好吃。","city":"沈阳","image":"assets/images/foods/liaoning_idxh.jpg"},{"name":"李连贵熏肉大饼","rating":4.8,"tags":["非遗名吃","外酥里嫩"],"intro":"熏肉色泽棕红，肉质醇香，大饼用肉汤和面烙制，皮酥里软，夹着葱丝和甜面酱吃，一绝。","city":"沈阳","image":"assets/images/foods/liaoning_bsir.jpg"},{"name":"锅包肉","rating":4.9,"tags":["东北名菜","酸甜酥脆"],"intro":"虽然发源于哈尔滨，但沈阳版锅包肉常用番茄酱调汁（老式用糖醋），炸得极其酥脆，酸甜开胃。","city":"沈阳","image":"assets/images/foods/liaoning_92y7.jpg"},{"name":"白肉血肠","rating":4.7,"tags":["满族特色","肥而不腻"],"intro":"杀猪菜的精髓，白肉（五花肉）切薄片，血肠软嫩，配以酸菜炖煮，蘸蒜泥酱油，极其解馋。","city":"沈阳","image":"assets/images/foods/liaoning_10ru.jpg"}],"itineraries":[{"step":"1","title":"Day 1: 皇家盛京与张氏帅府","desc":"上午参观关外皇家遗珍【沈阳故宫】；下午游览民国张氏帅府大青楼，随后在沈阳中街步行街购物吃饺子。"},{"step":"2","title":"Day 2: 滨海大连洋浪漫","desc":"坐高铁前往大连，打卡星海广场，乘坐百年有轨电车慢游市区，傍晚去【金石滩黄金海岸】吹海风、吃海鲜烧烤。"}]}
